slideflow_gpl/__init__.py
slideflow_gpl/_version.py
slideflow_gpl/clam/__init__.py
slideflow_gpl/clam/config.py
slideflow_gpl/clam/data.py
slideflow_gpl/clam/inference.py
slideflow_gpl/clam/model.py
slideflow_gpl/clam/legacy/__init__.py
slideflow_gpl/clam/legacy/create_attention.py
slideflow_gpl/clam/legacy/trainer.py
slideflow_gpl/clam/legacy/datasets/__init__.py
slideflow_gpl/clam/legacy/datasets/dataset_generic.py
slideflow_gpl/clam/legacy/utils/__init__.py
slideflow_gpl/clam/legacy/utils/core_utils.py
slideflow_gpl/clam/legacy/utils/eval_utils.py
slideflow_gpl/clam/legacy/utils/file_utils.py
slideflow_gpl/clam/legacy/utils/loss_utils.py
slideflow_gpl/extractors/__init__.py
slideflow_gpl/extractors/ctranspath.py
slideflow_gpl/extractors/retccl.py
slideflow_gpl-0.0.2.dist-info/LICENSE
slideflow_gpl-0.0.2.dist-info/METADATA
slideflow_gpl-0.0.2.dist-info/WHEEL
slideflow_gpl-0.0.2.dist-info/entry_points.txt
slideflow_gpl-0.0.2.dist-info/top_level.txt
slideflow_gpl-0.0.2.dist-info/RECORD
