Metadata-Version: 2.1
Name: slideflow-gpl
Version: 0.0.2
Summary: GPL-3 extensions and tools for Slideflow.
Home-page: https://github.com/slideflow/slideflow-gpl
Author: James Dolezal
Author-email: james@slideflow.ai
Classifier: Programming Language :: Python :: 3
Classifier: License :: OSI Approved :: GNU General Public License v3 (GPLv3)
Classifier: Operating System :: OS Independent
Requires-Python: >=3.7
License-File: LICENSE
Requires-Dist: slideflow >=3.0
Requires-Dist: numpy
Requires-Dist: pillow >=6.0.0
Requires-Dist: gdown
Requires-Dist: torch
Requires-Dist: torchvision
Requires-Dist: timm
Requires-Dist: huggingface-hub
Requires-Dist: transformers
Requires-Dist: fastai
Requires-Dist: scikit-misc
